aliyunsdkgeoip/__init__.py
aliyunsdkgeoip/request/__init__.py
aliyunsdkgeoip/request/v20200101/DescribeGeoipInstanceDataInfosRequest.py
aliyunsdkgeoip/request/v20200101/DescribeGeoipInstanceDataUrlRequest.py
aliyunsdkgeoip/request/v20200101/DescribeGeoipInstanceRequest.py
aliyunsdkgeoip/request/v20200101/DescribeGeoipInstanceStatisticsRequest.py
aliyunsdkgeoip/request/v20200101/DescribeGeoipInstancesRequest.py
aliyunsdkgeoip/request/v20200101/DescribeIpv4LocationRequest.py
aliyunsdkgeoip/request/v20200101/DescribeIpv6LocationRequest.py
aliyunsdkgeoip/request/v20200101/__init__.py
aliyun_python_sdk_geoip-1.0.4.dist-info/LICENSE
aliyun_python_sdk_geoip-1.0.4.dist-info/METADATA
aliyun_python_sdk_geoip-1.0.4.dist-info/WHEEL
aliyun_python_sdk_geoip-1.0.4.dist-info/top_level.txt
aliyun_python_sdk_geoip-1.0.4.dist-info/RECORD
